TestPackage_yidas/TestClass.py
TestPackage_yidas/__init__.py
TestPackage_yidas/example.py
testpackage_yidas-0.0.6.dist-info/METADATA
testpackage_yidas-0.0.6.dist-info/WHEEL
testpackage_yidas-0.0.6.dist-info/RECORD
